dapp_runner/__init__.py
dapp_runner/__main__.py
dapp_runner/_util.py
dapp_runner/api/__init__.py
dapp_runner/api/__main__.py
dapp_runner/descriptor/__init__.py
dapp_runner/descriptor/base.py
dapp_runner/descriptor/config.py
dapp_runner/descriptor/dapp.py
dapp_runner/descriptor/error.py
dapp_runner/descriptor/manifest.py
dapp_runner/descriptor/parser.py
dapp_runner/log.py
dapp_runner/runner/__init__.py
dapp_runner/runner/error.py
dapp_runner/runner/infile.py
dapp_runner/runner/payload.py
dapp_runner/runner/runner.py
dapp_runner/runner/service.py
dapp_runner/runner/strategy.py
dapp_runner/runner/streams.py
dapp_runner/singleton.py
dapp_runner-0.3.1.dist-info/LICENSE
dapp_runner-0.3.1.dist-info/METADATA
dapp_runner-0.3.1.dist-info/WHEEL
dapp_runner-0.3.1.dist-info/entry_points.txt
dapp_runner-0.3.1.dist-info/RECORD
