Metadata-Version: 2.1
Name: dapp-runner
Version: 0.3.1
Summary: Golem dapp-runner - a high-level interface for running decentralized applications using the Golem Network.
Home-page: https://github.com/golemfactory/dapp-runner
License: LGPL-3.0
Author: Golem Factory
Author-email: contact@golem.network
Requires-Python: >=3.8,<4.0
Classifier: Development Status :: 2 - Pre-Alpha
Classifier: Environment :: Console
Classifier: Intended Audience :: Developers
Classifier: License :: OSI Approved :: GNU Lesser General Public License v3 (LGPLv3)
Classifier: Natural Language :: English
Classifier: Programming Language :: Python :: 3
Classifier: Programming Language :: Python :: 3.8
Classifier: Programming Language :: Python :: 3.9
Classifier: Programming Language :: Python :: 3.10
Classifier: Programming Language :: Python :: 3.11
Classifier: Programming Language :: Python :: 3.12
Classifier: Programming Language :: Python :: 3.13
Classifier: Topic :: Software Development
Classifier: Topic :: System :: Distributed Computing
Requires-Dist: ansicolors (>=1.1.8,<2.0.0)
Requires-Dist: appdirs (>=1.4,<2.0)
Requires-Dist: click (>=7.0,<8.0)
Requires-Dist: dpath (>=2.0.8,<2.1.0)
Requires-Dist: fastapi (>=0.93.0,<0.94.0)
Requires-Dist: networkx (>=2.8,<3.0)
Requires-Dist: pydantic (>=1.10.5,<2.0.0)
Requires-Dist: pyopenssl (>=23.1.1,<24.0.0)
Requires-Dist: pyyaml (>=6.0,<7.0)
Requires-Dist: shortuuid (>=1.0,<2.0)
Requires-Dist: uvicorn[standard] (>=0.21.0,<0.22.0)
Requires-Dist: yapapi (==0.13.1)
Project-URL: Repository, https://github.com/golemfactory/dapp-runner
